terraplanfeed/__init__.py
terraplanfeed/__main__.py
terraplanfeed/azuredevops.py
terraplanfeed/cli.py
terraplanfeed/log.py
terraplanfeed/main.py
terraplanfeed/stdout.py
terraplanfeed/terraform.py
terraplanfeed-0.9.2.dist-info/LICENSE
terraplanfeed-0.9.2.dist-info/METADATA
terraplanfeed-0.9.2.dist-info/WHEEL
terraplanfeed-0.9.2.dist-info/entry_points.txt
terraplanfeed-0.9.2.dist-info/top_level.txt
terraplanfeed-0.9.2.dist-info/RECORD
