Metadata-Version: 2.1
Name: terraplanfeed
Version: 0.9.2
Summary: Parse Terraform plan in json format and give feedback.
Home-page: https://github.com/bcochofel/terraplanfeed
Author: Bruno Cochofel
Author-email: bruno.cochofel@gmail.com
License: UNKNOWN
Keywords: terraplanfeed,Python,Terraform,Terraform Plan
Platform: UNKNOWN
Classifier: Development Status :: 4 - Beta
Classifier: Environment :: Console
Classifier: Intended Audience :: Developers
Classifier: Intended Audience :: System Administrators
Classifier: License :: OSI Approved :: MIT License
Classifier: Programming Language :: Python :: 3 :: Only
Classifier: Programming Language :: Python :: 3.7
Classifier: Programming Language :: Python :: 3.8
Classifier: Programming Language :: Python :: 3.9
Classifier: Topic :: Software Development :: Build Tools
Requires-Python: >=3.7, <4
License-File: LICENSE
Requires-Dist: click
Requires-Dist: requests
Requires-Dist: envparse
